odoo/addons/res_currency_rate_provider_BCV/README.rst
odoo/addons/res_currency_rate_provider_BCV/__init__.py
odoo/addons/res_currency_rate_provider_BCV/__manifest__.py
odoo/addons/res_currency_rate_provider_BCV/i18n/res_currency_rate_provider_BCV.pot
odoo/addons/res_currency_rate_provider_BCV/models/__init__.py
odoo/addons/res_currency_rate_provider_BCV/models/models.py
odoo/addons/res_currency_rate_provider_BCV/readme/CONFIGURE.rst
odoo/addons/res_currency_rate_provider_BCV/readme/CONTRIBUTORS.rst
odoo/addons/res_currency_rate_provider_BCV/readme/DESCRIPTION.rst
odoo/addons/res_currency_rate_provider_BCV/readme/USAGE.rst
odoo/addons/res_currency_rate_provider_BCV/static/description/icon.png
odoo/addons/res_currency_rate_provider_BCV/static/description/index.html
odoo/addons/res_currency_rate_provider_BCV/views/views.xml
odoo_addon_res_currency_rate_provider_BCV-16.0.1.1.2.2.dist-info/METADATA
odoo_addon_res_currency_rate_provider_BCV-16.0.1.1.2.2.dist-info/WHEEL
odoo_addon_res_currency_rate_provider_BCV-16.0.1.1.2.2.dist-info/top_level.txt
odoo_addon_res_currency_rate_provider_BCV-16.0.1.1.2.2.dist-info/RECORD
