Metadata-Version: 2.1
Name: odoo-addon-res-currency-rate-provider-BCV
Version: 16.0.1.1.2.2
Summary: OCA version for BCV scrapping rates
Home-page: https://github.com/OCA/l10n-venezuela
Author: Luis Pinzón, Odoo Community Association (OCA)
Author-email: support@odoo-community.org
License: AGPL-3
Platform: UNKNOWN
Classifier: Programming Language :: Python
Classifier: Framework :: Odoo
Classifier: Framework :: Odoo :: 16.0
Classifier: License :: OSI Approved :: GNU Affero General Public License v3
Classifier: Development Status :: 4 - Beta
Requires-Python: >=3.10
Requires-Dist: odoo-addon-currency-rate-update <16.1dev,>=16.0dev
Requires-Dist: odoo <16.1dev,>=16.0a
